autogpt_plugins/__init__.py
autogpt_plugins/create_plugins_here
autogpt_plugins/twitter/__init__.py
autogpt_plugins-0.0.2.dist-info/METADATA
autogpt_plugins-0.0.2.dist-info/WHEEL
autogpt_plugins-0.0.2.dist-info/licenses/LICENSE
autogpt_plugins-0.0.2.dist-info/RECORD
